{
  "schema_version": "1.0",
  "generated_at": "2025-09-23T18:26:53.758Z",
  "provenance": {
    "source": "respuestas-por-puntos.csv",
    "generator": "generate-individual-reports.mjs"
  },
  "header": {
    "empresa": "Banco de Guayaquil",
    "generatedAt": "2025-09-23T18:26:53.758Z",
    "schema": "individual-1.0",
    "id": "h6afbht1gr9y57lcqyzoo2h6afb9eyyc",
    "subject": {
      "nombreCompleto": "OLINDA MARINOS",
      "email": "omarinos@bancoguayaquil.com",
      "assessed_on": "2025-09-23T18:26:53.758Z",
      "demographics": {
        "rol": "Asesor Digital",
        "area": "Customer Care",
        "nivelEducativo": "Universitario (Pregrado)",
        "genero": "Femenino",
        "rangoEdad": "35-44"
      }
    }
  },
  "scores": {
    "madurezDigital": {
      "adaptabilidad": 2.67,
      "resolucionDeProblemas": 3.5,
      "proactividadDigital": 2.5
    },
    "brechaDigital": {
      "analisisDeDatos": 2,
      "alfabetizacionDeDatos": 2,
      "colaboracionDigital": 2.5,
      "ciberseguridad": 3.25
    },
    "culturaOrganizacional": {
      "liderazgoYVision": 3,
      "ambienteDeAprendizaje": 3,
      "apoyoOrganizacional": 3,
      "experimentacion": 3,
      "reconocimiento": 3
    },
    "usoInteligenciaArtificial": {
      "frecuenciaDeUso": 3,
      "habilidadDeUso": 3,
      "nivelDeAdopcion": 2,
      "percepcionDeRiesgo": 2,
      "interesEnAprendizaje": 3,
      "eticaYVerificacion": 2
    },
    "rolLiderazgo": {
      "usoDeBI": 0,
      "exploracionTecnologica": 0,
      "gestionDeRiesgo": 0,
      "estrategiaTecnologica": 0
    },
    "rolMandosMedios": {
      "gestionDeProyectos": 0,
      "monitoreoDeRendimiento": 0,
      "liderazgoDeAdopcion": 0,
      "optimizacionDeColaboracion": 0,
      "usoDeIAEnGestion": 0
    },
    "rolComercialCliente": {
      "usoDeCRM": 3,
      "analiticaDeCliente": 3,
      "comunicacionConClientes": 3,
      "automatizacionDeMarketing": 1,
      "usoDeIA": 3,
      "usoDeSEO": 1,
      "gestionDePaidMedia": 2
    },
    "rolOperacionesAdminFinanzas": {
      "usoDeERP": 0,
      "hojasDeCalculoAvanzadas": 0,
      "plataformasDeGestion": 0,
      "digitalizacionDeProcesos": 0,
      "usoDeIA": 0
    },
    "rolTecnicoProducto": {
      "gestionDeCodigo": 0,
      "cloudComputing": 0,
      "mejoraDeInfraestructura": 0,
      "metodologiasDeDesarrollo": 0,
      "usoDeIAEnDesarrollo": 0,
      "scripting": 0,
      "basesDeDatos": 0,
      "diseñoUI": 0
    },
    "rolSoporteInterno": {
      "usoDeHRIS": 0,
      "reclutamientoDigital": 0,
      "plataformasDeCapacitacion": 0,
      "gestionDocumental": 0,
      "usoDeIA": 0
    }
  },
  "scores10": {
    "madurezDigital": {
      "adaptabilidad": 6.7,
      "resolucionDeProblemas": 8.8,
      "proactividadDigital": 6.3
    },
    "brechaDigital": {
      "analisisDeDatos": 5,
      "alfabetizacionDeDatos": 5,
      "colaboracionDigital": 6.3,
      "ciberseguridad": 8.1
    },
    "culturaOrganizacional": {
      "liderazgoYVision": 7.5,
      "ambienteDeAprendizaje": 7.5,
      "apoyoOrganizacional": 7.5,
      "experimentacion": 7.5,
      "reconocimiento": 7.5
    },
    "usoInteligenciaArtificial": {
      "frecuenciaDeUso": 7.5,
      "habilidadDeUso": 7.5,
      "nivelDeAdopcion": 5,
      "percepcionDeRiesgo": 5,
      "interesEnAprendizaje": 7.5,
      "eticaYVerificacion": 5
    },
    "rolLiderazgo": {
      "usoDeBI": 0,
      "exploracionTecnologica": 0,
      "gestionDeRiesgo": 0,
      "estrategiaTecnologica": 0
    },
    "rolMandosMedios": {
      "gestionDeProyectos": 0,
      "monitoreoDeRendimiento": 0,
      "liderazgoDeAdopcion": 0,
      "optimizacionDeColaboracion": 0,
      "usoDeIAEnGestion": 0
    },
    "rolComercialCliente": {
      "usoDeCRM": 7.5,
      "analiticaDeCliente": 7.5,
      "comunicacionConClientes": 7.5,
      "automatizacionDeMarketing": 2.5,
      "usoDeIA": 7.5,
      "usoDeSEO": 2.5,
      "gestionDePaidMedia": 5
    },
    "rolOperacionesAdminFinanzas": {
      "usoDeERP": 0,
      "hojasDeCalculoAvanzadas": 0,
      "plataformasDeGestion": 0,
      "digitalizacionDeProcesos": 0,
      "usoDeIA": 0
    },
    "rolTecnicoProducto": {
      "gestionDeCodigo": 0,
      "cloudComputing": 0,
      "mejoraDeInfraestructura": 0,
      "metodologiasDeDesarrollo": 0,
      "usoDeIAEnDesarrollo": 0,
      "scripting": 0,
      "basesDeDatos": 0,
      "diseñoUI": 0
    },
    "rolSoporteInterno": {
      "usoDeHRIS": 0,
      "reclutamientoDigital": 0,
      "plataformasDeCapacitacion": 0,
      "gestionDocumental": 0,
      "usoDeIA": 0
    }
  },
  "summary": {
    "dimensions": {
      "madurezDigital": {
        "current10": 7.2,
        "target10": 8,
        "gap10": 0.8,
        "collectiveAverage10": 7.62,
        "percentile": 36,
        "level_label": "En desarrollo"
      },
      "brechaDigital": {
        "current10": 6.1,
        "target10": 8,
        "gap10": 1.9,
        "collectiveAverage10": 7.8,
        "percentile": 5,
        "level_label": "Inicial"
      },
      "usoInteligenciaArtificial": {
        "current10": 6.3,
        "target10": 8,
        "gap10": 1.7,
        "collectiveAverage10": 6.99,
        "percentile": 24,
        "level_label": "En desarrollo"
      },
      "culturaOrganizacional": {
        "current10": 7.5,
        "target10": 8,
        "gap10": 0.5,
        "collectiveAverage10": 7.59,
        "percentile": 48,
        "level_label": "En desarrollo"
      }
    }
  },
  "openEnded": {},
  "action_plan": {
    "resumenGeneral": "Plan priorizado según brechas principales — brechaDigital: gap 1.9 · usoInteligenciaArtificial: gap 1.7.",
    "criteriosDescripcion": "Selección multifactorial con tope de 4 iniciativas. Prioridad por brecha (gap10) y peso por dimensión: brechaDigital (gap=1.90), usoInteligenciaArtificial (gap=1.70), madurezDigital (gap=0.80), culturaOrganizacional (gap=0.50). Pesos: {\"madurezDigital\":1,\"brechaDigital\":1,\"usoInteligenciaArtificial\":1.2,\"culturaOrganizacional\":0.9}. Bono por afinidad de rol ('rolesPreferidos' incluye 'tecnico'): +0.4. Bono por aspiración profesional ('rutaDeCarrera' incluye 'comercial'): +0.6. Bono por subdimensiones objetivo si cubre las peores (top-2) de la dimensión: +0.3. Heurística de impacto/esfuerzo: impacto alto (+0.2), medio (+0.1); esfuerzo alto (-0.2), esfuerzo bajo (+0.1). Enriquecimiento de KPIs/OKRs: si aplica, se asigna métrica a la peor subdimensión cubierta y objetivo como max(actual+0.5, target10). Complemento transversal: si sobran cupos, se agregan acciones de cualquier dimensión alineadas a la aspiración ('rutaDeCarrera'~='comercial'). Fallback sin brechas: se proponen 1–2 KPIs relevantes guiados por señales.",
    "criterios": {
      "top_gaps": [
        {
          "dim": "brechaDigital",
          "gap": 1.9
        },
        {
          "dim": "usoInteligenciaArtificial",
          "gap": 1.7
        },
        {
          "dim": "madurezDigital",
          "gap": 0.8
        },
        {
          "dim": "culturaOrganizacional",
          "gap": 0.5
        }
      ],
      "role": "tecnico",
      "signals_from_open_ended": [],
      "aspiracionProfesional": "ir aprendiendo procesos internos para dar mas alcance a nuestros clientes",
      "aspiracion_slug": "comercial"
    },
    "iniciativas": [
      {
        "id": "CD-04",
        "titulo": "Mentoring entre pares",
        "descripcion": "Pareo mensual para práctica dirigida de competencias digitales con retos cortos.",
        "areaEnfoque": "Talento y Formación",
        "prioridad": "Baja",
        "plazoEstimado": "8 semanas",
        "rolesPreferidos": [
          "mandos",
          "tecnico"
        ],
        "tags": [
          "colaboracion",
          "aprendizaje"
        ],
        "rutaDeCarrera": [
          "liderazgo",
          "mandos",
          "tecnico"
        ],
        "type": "OKR",
        "subdimensiones": [
          "colaboracionDigital"
        ],
        "key_results": [
          {
            "metric": "analisisDeDatos",
            "target": "8.0/10"
          },
          {
            "metric": "alfabetizacionDeDatos",
            "target": "8.0/10"
          }
        ]
      },
      {
        "id": "IA-05",
        "titulo": "Tomar curso por rol de Prompting",
        "descripcion": "Curso práctico por rol (ventas, soporte, PM) con entregables y evaluación de calidad de prompts.",
        "areaEnfoque": "Talento y Ética",
        "prioridad": "Media",
        "plazoEstimado": "2-3 semanas",
        "rolesPreferidos": [
          "comercial",
          "tecnico",
          "mandos"
        ],
        "tags": [
          "capacitacion",
          "prompt"
        ],
        "rutaDeCarrera": [
          "gestion_producto",
          "comercial"
        ],
        "type": "KPI",
        "subdimensiones": [
          "habilidadDeUso"
        ],
        "metric": "habilidaddeuso",
        "target": "8.0/10"
      },
      {
        "id": "IA-02",
        "titulo": "Capacitación en prompt engineering y ética",
        "descripcion": "Talleres con plantillas de prompts, criterios de verificación y pautas de uso responsable.",
        "areaEnfoque": "Talento y Ética",
        "prioridad": "Media",
        "plazoEstimado": "4-6 semanas",
        "rolesPreferidos": [
          "rrhh",
          "mandos",
          "comercial"
        ],
        "tags": [
          "capacitacion",
          "etica",
          "prompt"
        ],
        "rutaDeCarrera": [
          "gestion_producto",
          "comercial"
        ],
        "type": "KPI",
        "subdimensiones": [
          "eticaYVerificacion",
          "percepcionDeRiesgo"
        ],
        "metric": "eticayverificacion",
        "target": "8.0/10"
      },
      {
        "id": "IA-09",
        "titulo": "Curso de verificación y sesgos",
        "descripcion": "Completar curso con checklist de verificación, sesgos comunes y límites de uso por caso.",
        "areaEnfoque": "Talento y Ética",
        "prioridad": "Media",
        "plazoEstimado": "2-3 semanas",
        "rolesPreferidos": [
          "rrhh",
          "mandos",
          "tecnico"
        ],
        "tags": [
          "etica",
          "verificacion"
        ],
        "rutaDeCarrera": [
          "liderazgo",
          "tecnico"
        ],
        "type": "KPI",
        "subdimensiones": [
          "eticaYVerificacion",
          "percepcionDeRiesgo"
        ],
        "metric": "eticayverificacion",
        "target": "8.0/10"
      }
    ]
  }
}